{
  "cancel": "Cancel",
  "confirmPassword": "Confirm password",
  "contacts": "Contacts",
  "email": "E-mail",
  "error.emptyConfirmPassword": "\"Confirm password\" field can't be empty",
  "error.emptyLogin": "\"E-mail\" field can't be empty",
  "error.emptyPassword": "\"Password\" field can't be empty",
  "error.internal": "Some internal error occurred",
  "error.isNotEmail": "Wrong email format",
  "error.passwordsNotMatch": "\"Password\" and \"Confirm password\" fields must match",
  "error.wrongLoginOrPassword": "Wrong email or password",
  "fetch.errorOccurred": "Some internal error occurred during loading process.",
  "fetch.loading": "Loading...",
  "login": "Login",
  "name": "Name",
  "page.aboutMe": "About me",
  "page.main": "Main",
  "page.workbooks": "Workbooks",
  "password": "Password",
  "phoneNumber": "Phone",
  "signIn": "Sign in",
  "signUp": "Sign up"
}